argo_mon_library/__init__.py
argo_mon_library/argomonitoringservice.py
argo_mon_library/exceptions.py
argo_mon_library/httprequests.py
argo_mon_library/reportresults.py
argo_mon_library/reports.py
argo_mon_library/reportstatus.py
argo_mon_library/restresource.py
argo_mon_library-0.1.0.dist-info/LICENSE
argo_mon_library-0.1.0.dist-info/METADATA
argo_mon_library-0.1.0.dist-info/WHEEL
argo_mon_library-0.1.0.dist-info/top_level.txt
argo_mon_library-0.1.0.dist-info/RECORD
