Metadata-Version: 2.1
Name: argo-mon-library
Version: 0.1.0
Summary: A simple python library for interacting with the ARGO Monitoring Service
Home-page: https://github.com/ARGOeu/argo-mon-library
Author: GRNET
Author-email: wvkarageorgos@admin.grnet.gr
License: ASL 2.0
Platform: UNKNOWN
Classifier: Development Status :: 3 - Alpha
Classifier: License :: OSI Approved :: Apache Software License
Classifier: Operating System :: POSIX
Classifier: Programming Language :: Python :: 3.9
Classifier: Programming Language :: Python :: 3.11
Classifier: Programming Language :: Python :: 3.12
Classifier: Intended Audience :: Developers
Classifier: Topic :: Software Development :: Libraries :: Python Modules
Requires-Dist: requests
